HyperStackView/__init__.py
HyperStackView/__main__.py
HyperStackView/app.py
HyperStackView/app_state.py
HyperStackView/bg_cube_f.glsl
HyperStackView/bg_cube_v.glsl
HyperStackView/color_button.py
HyperStackView/color_picker.py
HyperStackView/cube.png
HyperStackView/cube_f.glsl
HyperStackView/cube_v.glsl
HyperStackView/defaults.yaml
HyperStackView/final_f.glsl
HyperStackView/final_v.glsl
HyperStackView/flatten_f.glsl
HyperStackView/flatten_v.glsl
HyperStackView/genteststack.py
HyperStackView/gl_bitmaps.py
HyperStackView/gl_view.py
HyperStackView/grid.png
HyperStackView/grid_f.glsl
HyperStackView/grid_v.glsl
HyperStackView/hyperstack.py
HyperStackView/hyperstackview.py
HyperStackView/ic_bg_cube.png
HyperStackView/ic_grid.png
HyperStackView/ic_rot_front.png
HyperStackView/ic_rot_home.png
HyperStackView/ic_rot_side.png
HyperStackView/ic_rot_zero.png
HyperStackView/near_far.png
HyperStackView/object_selector.py
HyperStackView/paths.py
HyperStackView/projection_plane_indicator_f.glsl
HyperStackView/projection_plane_indicator_v.glsl
HyperStackView/shader_util.py
HyperStackView/sliders.py
HyperStackView/transform.py
HyperStackView/config_ui/__init__.py
HyperStackView/config_ui/_abstract.py
HyperStackView/config_ui/animation.py
HyperStackView/config_ui/channels.py
HyperStackView/config_ui/input.py
HyperStackView/config_ui/position.py
HyperStackView/config_ui/view.py
HyperStackView-1.0.0.dist-info/LICENSE
HyperStackView-1.0.0.dist-info/METADATA
HyperStackView-1.0.0.dist-info/WHEEL
HyperStackView-1.0.0.dist-info/entry_points.txt
HyperStackView-1.0.0.dist-info/top_level.txt
HyperStackView-1.0.0.dist-info/RECORD
