Metadata-Version: 2.1
Name: HyperStackView
Version: 1.0.0
Summary: Graphical application for rendering three-dimensional raster images
Home-page: https://gita.utia.cas.cz/schier/HyperStackView
Author: Jiří Wolker
Author-email: woljiri@gmail.com
License: UNKNOWN
Platform: UNKNOWN
Classifier: Programming Language :: Python :: 3
Classifier: Operating System :: OS Independent
Classifier: License :: OSI Approved :: GNU General Public License v3 (GPLv3)
License-File: LICENSE
Requires-Dist: PySide6
Requires-Dist: tifffile
Requires-Dist: imageio
Requires-Dist: PyOpenGL
Requires-Dist: PyYAML
